{
	"info": {
		"_postman_id": "0f4e2e8e-14ca-4675-a26d-5b3b713e853d",
		"name": "Delivery Company",
		"description": "Uptime Bot API.",
		"schema": "https://schema.getpostman.com/json/collection/v2.1.0/collection.json"
	},
	"item": [
		{
			"name": "GET /users",
			"request": {
				"method": "GET",
				"header": [
					{
						"key": "token",
						"value": "",
						"type": "text"
					}
				],
				"body": {
					"mode": "raw",
					"raw": ""
				},
				"url": {
					"raw": "http://localhost:3000/users",
					"protocol": "http",
					"host": [
						"localhost"
					],
					"port": "3000",
					"path": [
						"users"
					]
				}
			},
			"response": []
		},
		{
			"name": "POST /menu",
			"request": {
				"auth": {
					"type": "bearer",
					"bearer": [
						{
							"key": "token",
							"value": "25f3fa4cd0d466b5bc75d50747f3b798a6eecf2271fc3d74d3e075cac17f15b2",
							"type": "string"
						}
					]
				},
				"method": "POST",
				"header": [
					{
						"key": "token",
						"type": "text",
						"value": ""
					},
					{
						"key": "Content-Type",
						"name": "Content-Type",
						"value": "application/json",
						"type": "text"
					}
				],
				"body": {
					"mode": "raw",
					"raw": "{\r\n    \"action\": \"get\"\r\n}"
				},
				"url": {
					"raw": "http://localhost:3000/menu",
					"protocol": "http",
					"host": [
						"localhost"
					],
					"port": "3000",
					"path": [
						"menu"
					]
				}
			},
			"response": []
		},
		{
			"name": "POST /orders add_cart",
			"request": {
				"auth": {
					"type": "bearer",
					"bearer": [
						{
							"key": "token",
							"value": "ec76af07e246ed03d29871521971f8081abffc73225a66597a9edfcad58651f3",
							"type": "string"
						}
					]
				},
				"method": "POST",
				"header": [
					{
						"key": "token",
						"type": "text",
						"value": ""
					},
					{
						"key": "Content-Type",
						"name": "Content-Type",
						"type": "text",
						"value": "application/json"
					}
				],
				"body": {
					"mode": "raw",
					"raw": "{\r\n    \"action\": \"add_cart\",\r\n    \"items\": [0, 1, 2]\r\n}"
				},
				"url": {
					"raw": "http://localhost:3000/orders",
					"protocol": "http",
					"host": [
						"localhost"
					],
					"port": "3000",
					"path": [
						"orders"
					]
				}
			},
			"response": []
		},
		{
			"name": "POST /orders get_cart",
			"request": {
				"auth": {
					"type": "bearer",
					"bearer": [
						{
							"key": "token",
							"value": "3deb436047f41cbd7ea2847950a2afc17c4da4cac81efbe35b0b8c9424ceea21",
							"type": "string"
						}
					]
				},
				"method": "POST",
				"header": [
					{
						"key": "token",
						"type": "text",
						"value": ""
					},
					{
						"key": "Content-Type",
						"name": "Content-Type",
						"type": "text",
						"value": "application/json"
					}
				],
				"body": {
					"mode": "raw",
					"raw": "{\r\n    \"action\": \"get_cart\",\r\n    \"phone\": \"37061415694\"\r\n}"
				},
				"url": {
					"raw": "http://localhost:3000/orders",
					"protocol": "http",
					"host": [
						"localhost"
					],
					"port": "3000",
					"path": [
						"orders"
					]
				}
			},
			"response": []
		},
		{
			"name": "POST /orders buy",
			"request": {
				"auth": {
					"type": "bearer",
					"bearer": [
						{
							"key": "token",
							"value": "ec76af07e246ed03d29871521971f8081abffc73225a66597a9edfcad58651f3",
							"type": "string"
						}
					]
				},
				"method": "POST",
				"header": [
					{
						"key": "token",
						"type": "text",
						"value": ""
					},
					{
						"key": "Content-Type",
						"name": "Content-Type",
						"type": "text",
						"value": "application/json"
					}
				],
				"body": {
					"mode": "raw",
					"raw": "{\r\n    \"action\": \"get_cart\",\r\n    \"phone\": \"37061415694\"\r\n}"
				},
				"url": {
					"raw": "http://localhost:3000/orders",
					"protocol": "http",
					"host": [
						"localhost"
					],
					"port": "3000",
					"path": [
						"orders"
					]
				}
			},
			"response": []
		},
		{
			"name": "POST /orders get_orders",
			"request": {
				"auth": {
					"type": "bearer",
					"bearer": [
						{
							"key": "token",
							"value": "3deb436047f41cbd7ea2847950a2afc17c4da4cac81efbe35b0b8c9424ceea21",
							"type": "string"
						}
					]
				},
				"method": "POST",
				"header": [
					{
						"key": "token",
						"type": "text",
						"value": ""
					},
					{
						"key": "Content-Type",
						"name": "Content-Type",
						"type": "text",
						"value": "application/json"
					}
				],
				"body": {
					"mode": "raw",
					"raw": "{\r\n    \"action\": \"get_orders\",\r\n    \"phone\": \"37061415694\"\r\n}"
				},
				"url": {
					"raw": "http://localhost:3000/orders",
					"protocol": "http",
					"host": [
						"localhost"
					],
					"port": "3000",
					"path": [
						"orders"
					]
				}
			},
			"response": []
		},
		{
			"name": "POST /orders delete_cart",
			"request": {
				"auth": {
					"type": "bearer",
					"bearer": [
						{
							"key": "token",
							"value": "3deb436047f41cbd7ea2847950a2afc17c4da4cac81efbe35b0b8c9424ceea21",
							"type": "string"
						}
					]
				},
				"method": "POST",
				"header": [
					{
						"key": "token",
						"type": "text",
						"value": ""
					},
					{
						"key": "Content-Type",
						"name": "Content-Type",
						"type": "text",
						"value": "application/json"
					}
				],
				"body": {
					"mode": "raw",
					"raw": "{\r\n    \"action\": \"delete_cart\",\r\n    \"phone\": \"37061415694\"\r\n}"
				},
				"url": {
					"raw": "http://localhost:3000/orders",
					"protocol": "http",
					"host": [
						"localhost"
					],
					"port": "3000",
					"path": [
						"orders"
					]
				}
			},
			"response": []
		},
		{
			"name": "POST /orders get_order",
			"request": {
				"auth": {
					"type": "bearer",
					"bearer": [
						{
							"key": "token",
							"value": "3deb436047f41cbd7ea2847950a2afc17c4da4cac81efbe35b0b8c9424ceea21",
							"type": "string"
						}
					]
				},
				"method": "POST",
				"header": [
					{
						"key": "token",
						"type": "text",
						"value": ""
					},
					{
						"key": "Content-Type",
						"name": "Content-Type",
						"type": "text",
						"value": "application/json"
					}
				],
				"body": {
					"mode": "raw",
					"raw": "{\r\n    \"action\": \"delete_cart\",\r\n    \"phone\": \"37061415694\"\r\n}"
				},
				"url": {
					"raw": "http://localhost:3000/orders",
					"protocol": "http",
					"host": [
						"localhost"
					],
					"port": "3000",
					"path": [
						"orders"
					]
				}
			},
			"response": []
		},
		{
			"name": "POST /users",
			"request": {
				"method": "POST",
				"header": [
					{
						"key": "token",
						"type": "text",
						"value": ""
					},
					{
						"key": "Content-Type",
						"name": "Content-Type",
						"value": "application/json",
						"type": "text"
					}
				],
				"body": {
					"mode": "raw",
					"raw": "{\r\n    \"phone\": \"37061415694\",\r\n    \"firstName\": \"John\",\r\n    \"lastName\": \"Doe\",\r\n    \"email\": \"talaikis.tadas@gmail.com\",\r\n    \"password\": \"testpassword369\",\r\n    \"tosAgreement\": true\r\n}"
				},
				"url": {
					"raw": "http://localhost:3000/users",
					"protocol": "http",
					"host": [
						"localhost"
					],
					"port": "3000",
					"path": [
						"users"
					]
				}
			},
			"response": []
		},
		{
			"name": "POST /urls",
			"request": {
				"auth": {
					"type": "bearer",
					"bearer": [
						{
							"key": "token",
							"value": "8160b12bdfdb3f070758b9b85d24934cb04308894cd515c5077e0a83f25c055b",
							"type": "string"
						}
					]
				},
				"method": "POST",
				"header": [
					{
						"key": "token",
						"type": "text",
						"value": ""
					},
					{
						"key": "Content-Type",
						"name": "Content-Type",
						"value": "application/json",
						"type": "text"
					}
				],
				"body": {
					"mode": "raw",
					"raw": "{\r\n    \"protocol\": \"https\",\r\n    \"url\": \"test.com\",\r\n    \"method\": \"GET\",\r\n    \"successCodes\": [200, 201, 301],\r\n    \"timeout\": 5\r\n}"
				},
				"url": {
					"raw": "http://localhost:3000/urls",
					"protocol": "http",
					"host": [
						"localhost"
					],
					"port": "3000",
					"path": [
						"urls"
					]
				}
			},
			"response": []
		},
		{
			"name": "PUT /urls",
			"request": {
				"auth": {
					"type": "bearer",
					"bearer": [
						{
							"key": "token",
							"value": "7591db136c97110ec487f3d771cf4fffbe70424deae4be2d97f8c2a1976453d1",
							"type": "string"
						}
					]
				},
				"method": "PUT",
				"header": [
					{
						"key": "token",
						"type": "text",
						"value": ""
					},
					{
						"key": "Content-Type",
						"name": "Content-Type",
						"value": "application/json",
						"type": "text"
					}
				],
				"body": {
					"mode": "raw",
					"raw": "{\r\n    \"urlId\": \"d668af45-6a81-4767-8b73-b8cf3ecc8dc9\",\r\n    \"protocol\": \"https\",\r\n    \"url\": \"google2.com\",\r\n    \"method\": \"GET\",\r\n    \"successCodes\": [200, 201, 301],\r\n    \"timeout\": 5\r\n}"
				},
				"url": {
					"raw": "http://localhost:3000/urls",
					"protocol": "http",
					"host": [
						"localhost"
					],
					"port": "3000",
					"path": [
						"urls"
					]
				}
			},
			"response": []
		},
		{
			"name": "DELETE /urls",
			"request": {
				"auth": {
					"type": "bearer",
					"bearer": [
						{
							"key": "token",
							"value": "7591db136c97110ec487f3d771cf4fffbe70424deae4be2d97f8c2a1976453d1",
							"type": "string"
						}
					]
				},
				"method": "DELETE",
				"header": [
					{
						"key": "token",
						"type": "text",
						"value": ""
					},
					{
						"key": "Content-Type",
						"name": "Content-Type",
						"type": "text",
						"value": "application/json"
					}
				],
				"body": {
					"mode": "raw",
					"raw": "{\r\n    \"urlId\": \"d668af45-6a81-4767-8b73-b8cf3ecc8dc9\"\r\n}"
				},
				"url": {
					"raw": "http://localhost:3000/urls",
					"protocol": "http",
					"host": [
						"localhost"
					],
					"port": "3000",
					"path": [
						"urls"
					]
				}
			},
			"response": []
		},
		{
			"name": "PUT /users",
			"request": {
				"auth": {
					"type": "bearer",
					"bearer": [
						{
							"key": "token",
							"value": "8160b12bdfdb3f070758b9b85d24934cb04308894cd515c5077e0a83f25c055b",
							"type": "string"
						}
					]
				},
				"method": "PUT",
				"header": [
					{
						"key": "token",
						"type": "text",
						"value": ""
					},
					{
						"key": "Content-Type",
						"name": "Content-Type",
						"value": "application/json",
						"type": "text"
					}
				],
				"body": {
					"mode": "raw",
					"raw": "{\r\n    \"phone\": \"37061415694\",\r\n    \"firstName\": \"John Renamed\",\r\n    \"lastName\": \"Doe Renamed\",\r\n    \"email\": \"info@test.com\",\r\n    \"password\": \"testpassword369\",\r\n    \"tosAgreement\": true\r\n}"
				},
				"url": {
					"raw": "http://localhost:3000/users",
					"protocol": "http",
					"host": [
						"localhost"
					],
					"port": "3000",
					"path": [
						"users"
					]
				}
			},
			"response": []
		},
		{
			"name": "DELETE /users",
			"request": {
				"auth": {
					"type": "bearer",
					"bearer": [
						{
							"key": "token",
							"value": "026ca123-7c6e-4700-ae6a-6e16433b8e5f",
							"type": "string"
						}
					]
				},
				"method": "DELETE",
				"header": [
					{
						"key": "token",
						"type": "text",
						"value": ""
					},
					{
						"key": "Content-Type",
						"name": "Content-Type",
						"value": "application/json",
						"type": "text"
					}
				],
				"body": {
					"mode": "raw",
					"raw": "{\r\n    \"phone\": \"37061415694\"\r\n}"
				},
				"url": {
					"raw": "http://localhost:3000/users",
					"protocol": "http",
					"host": [
						"localhost"
					],
					"port": "3000",
					"path": [
						"users"
					]
				}
			},
			"response": []
		},
		{
			"name": "GET /tokens",
			"request": {
				"method": "GET",
				"header": [],
				"body": {
					"mode": "raw",
					"raw": ""
				},
				"url": {
					"raw": ""
				}
			},
			"response": []
		},
		{
			"name": "PUT /tokens",
			"request": {
				"method": "PUT",
				"header": [
					{
						"key": "Content-Type",
						"name": "Content-Type",
						"value": "application/json",
						"type": "text"
					}
				],
				"body": {
					"mode": "raw",
					"raw": "{\r\n    \"tokenId\": \"02a2ba7d-468a-467b-823a-e90b117957f6\",\r\n    \"extend\": true\r\n}"
				},
				"url": {
					"raw": "http://localhost:3000/tokens",
					"protocol": "http",
					"host": [
						"localhost"
					],
					"port": "3000",
					"path": [
						"tokens"
					]
				}
			},
			"response": []
		},
		{
			"name": "DELETE /tokens",
			"request": {
				"method": "DELETE",
				"header": [
					{
						"key": "Content-Type",
						"name": "Content-Type",
						"value": "application/json",
						"type": "text"
					}
				],
				"body": {
					"mode": "raw",
					"raw": "{\r\n    \"tokenId\": \"6e96e278-228d-4a69-83d4-80ca0e449355\"\r\n}"
				},
				"url": {
					"raw": "http://localhost:3000/tokens",
					"protocol": "http",
					"host": [
						"localhost"
					],
					"port": "3000",
					"path": [
						"tokens"
					]
				}
			},
			"response": []
		},
		{
			"name": "POST /tokens",
			"request": {
				"method": "POST",
				"header": [
					{
						"key": "Content-Type",
						"name": "Content-Type",
						"value": "application/json",
						"type": "text"
					}
				],
				"body": {
					"mode": "raw",
					"raw": "{\r\n\t\"phone\": \"37061415694\",\r\n    \"password\": \"testpassword369\"\r\n}"
				},
				"url": {
					"raw": "http://localhost:3000/tokens",
					"protocol": "http",
					"host": [
						"localhost"
					],
					"port": "3000",
					"path": [
						"tokens"
					]
				}
			},
			"response": []
		},
		{
			"name": "POST /confirm",
			"request": {
				"method": "POST",
				"header": [
					{
						"key": "Content-Type",
						"name": "Content-Type",
						"value": "application/json",
						"type": "text"
					}
				],
				"body": {
					"mode": "raw",
					"raw": "{\r\n\t\"phone\": \"37061415694\",\r\n    \"password\": \"testpassword369\"\r\n}"
				},
				"url": {
					"raw": "http://localhost:3000/tokens",
					"protocol": "http",
					"host": [
						"localhost"
					],
					"port": "3000",
					"path": [
						"tokens"
					]
				}
			},
			"response": []
		},
		{
			"name": "POST /reset",
			"request": {
				"method": "POST",
				"header": [
					{
						"key": "Content-Type",
						"name": "Content-Type",
						"value": "application/json",
						"type": "text"
					}
				],
				"body": {
					"mode": "raw",
					"raw": "{\r\n\t\"phone\": \"37061415694\",\r\n    \"password\": \"testpassword369\"\r\n}"
				},
				"url": {
					"raw": "http://localhost:3000/tokens",
					"protocol": "http",
					"host": [
						"localhost"
					],
					"port": "3000",
					"path": [
						"tokens"
					]
				}
			},
			"response": []
		},
		{
			"name": "POST /refer refer",
			"request": {
				"auth": {
					"type": "bearer",
					"bearer": [
						{
							"key": "token",
							"value": "133f9a86b398e177c29a8e47befaccf3537f90a29677edc7d6e5778f53e50998",
							"type": "string"
						}
					]
				},
				"method": "POST",
				"header": [
					{
						"key": "Content-Type",
						"name": "Content-Type",
						"type": "text",
						"value": "application/json"
					}
				],
				"body": {
					"mode": "raw",
					"raw": "{\r\n    \"action\": \"refer\",\r\n    \"refEmail\": \"talaikis.tadas@gmail.com\",\r\n    \"phone\": \"37061415694\"\r\n}\r\n"
				},
				"url": {
					"raw": "http://localhost:3000/refer",
					"protocol": "http",
					"host": [
						"localhost"
					],
					"port": "3000",
					"path": [
						"refer"
					]
				}
			},
			"response": []
		},
		{
			"name": "POST /refer use",
			"request": {
				"auth": {
					"type": "bearer",
					"bearer": [
						{
							"key": "token",
							"value": "133f9a86b398e177c29a8e47befaccf3537f90a29677edc7d6e5778f53e50998",
							"type": "string"
						}
					]
				},
				"method": "POST",
				"header": [
					{
						"key": "Content-Type",
						"name": "Content-Type",
						"type": "text",
						"value": "application/json"
					}
				],
				"body": {
					"mode": "raw",
					"raw": "{\r\n    \"action\": \"refer\",\r\n    \"refEmail\": \"talaikis.tadas@gmail.com\",\r\n    \"phone\": \"37061415694\"\r\n}\r\n"
				},
				"url": {
					"raw": "http://localhost:3000/refer",
					"protocol": "http",
					"host": [
						"localhost"
					],
					"port": "3000",
					"path": [
						"refer"
					]
				}
			},
			"response": []
		},
		{
			"name": "POST /refer register",
			"request": {
				"auth": {
					"type": "bearer",
					"bearer": [
						{
							"key": "token",
							"value": "133f9a86b398e177c29a8e47befaccf3537f90a29677edc7d6e5778f53e50998",
							"type": "string"
						}
					]
				},
				"method": "POST",
				"header": [
					{
						"key": "Content-Type",
						"name": "Content-Type",
						"type": "text",
						"value": "application/json"
					}
				],
				"body": {
					"mode": "raw",
					"raw": "{\r\n    \"action\": \"register\",\r\n    \"token\": \"e137e903-b54d-40d8-9f0e-8a83abb0ef19\",\r\n    \"phone\": \"37061415694\"\r\n}"
				},
				"url": {
					"raw": "http://localhost:3000/refer",
					"protocol": "http",
					"host": [
						"localhost"
					],
					"port": "3000",
					"path": [
						"refer"
					]
				}
			},
			"response": []
		}
	],
	"auth": {
		"type": "bearer",
		"bearer": [
			{
				"key": "token",
				"value": "d467e3d0-2fad-4294-9035-037145e63924",
				"type": "string"
			}
		]
	}
}